snare/__init__.py
snare/arp.py
snare/forward.py
snare/sniffer.py
snare/tcp.py
snare/net/__init__.py
snare/net/addr.py
snare/net/iptables.py
snare/net/openvpn.py
snare/net/route.py
snare-0.2.8.dist-info/LICENSE.txt
snare-0.2.8.dist-info/METADATA
snare-0.2.8.dist-info/WHEEL
snare-0.2.8.dist-info/top_level.txt
snare-0.2.8.dist-info/RECORD
