Metadata-Version: 2.1
Name: snare
Version: 0.2.8
Summary: Network capture and manipulation module
Home-page: https://github.com/nategraf/snare
Author: Victor "Nate" Graf
Author-email: nategraf1@gmail.com
License: MIT
Classifier: Intended Audience :: Developers
Classifier: Topic :: Software Development :: Build Tools
Classifier: License :: OSI Approved :: MIT License
Classifier: Operating System :: OS Independent
Classifier: Natural Language :: English
Classifier: Programming Language :: Python :: 3
Classifier: Programming Language :: Python :: 3 :: Only
Classifier: Topic :: Security
Classifier: Topic :: Communications
Classifier: Topic :: Software Development :: Libraries :: Python Modules
Requires-Python: >=3
License-File: LICENSE.txt
Requires-Dist: scapy
